itk_vtkglue-0.3.0.dist-info/WHEEL
itk_vtkglue-0.3.0.dist-info/top_level.txt
itk_vtkglue-0.3.0.dist-info/RECORD
itk_vtkglue-0.3.0.dist-info/METADATA
itk/itkVTKImageImportPython.py
itk/itkViewImagePython.py
itk/itkBoxSpatialObjectToVTKPolyDataFilterPython.py
itk/itkVTKImageToImageFilterPython.py
itk/itkVTKImageExportPython.py
itk/itkImageToVTKImageFilterPython.py
itk/ITKVtkGluePython.py
itk/_ITKVtkGluePython.so
itk/itkSpatialObjectToVTKPolyDataFilterPython.py
itk/Configuration/ITKVtkGlueConfig.py
